README.md
setup.py
easy_data_analysis.egg-info/PKG-INFO
easy_data_analysis.egg-info/SOURCES.txt
easy_data_analysis.egg-info/dependency_links.txt
easy_data_analysis.egg-info/entry_points.txt
easy_data_analysis.egg-info/requires.txt
easy_data_analysis.egg-info/top_level.txt
eda/__init__.py
eda/cli.py
eda/config_default.yaml
eda/configure.py
eda/kinetics.py
eda/models.py
eda/spectrum.py
eda/utils.py
eda/docs/pypi_description.rst