Metadata-Version: 1.2
Name: easy-data-analysis
Version: 0.3.3
Summary: Scientific research data analysis tools
Home-page: https://github.com/jschnab/easy-data-analysis
Author: Jonathan Schnabel
Author-email: jonathan.schnabel31@gmail.com
License: GNU General Public Licence v3.0
Keywords: data analysis plotting statistics
Platform: UNKNOWN
Classifier: Development Status :: 3 - Alpha
Classifier: Intended Audience :: Science/Research
Classifier: License :: OSI Approved :: GNU General Public License v3 (GPLv3)
Classifier: Natural Language :: English
Classifier: Operating System :: Unix
Classifier: Operating System :: MacOS
Classifier: Programming Language :: Python :: 3.6
Requires-Python: >=3.6.8
